promptx/__init__.py
promptx/application.py
promptx/collection.py
promptx/template.py
promptx/utils.py
promptx/world.py
promptx/adapters/__init__.py
promptx/adapters/chromadb.py
promptx/models/__init__.py
promptx/models/openai.py
tests/__init__.py
tests/test_collection.py
tests/test_session.py
tests/test_template.py
pxx-0.0.9.dist-info/LICENSE
pxx-0.0.9.dist-info/METADATA
pxx-0.0.9.dist-info/WHEEL
pxx-0.0.9.dist-info/top_level.txt
pxx-0.0.9.dist-info/RECORD
